flake8_indent_in_def.py
flake8_indent_in_def-0.1.2.dist-info/LICENSE
flake8_indent_in_def-0.1.2.dist-info/METADATA
flake8_indent_in_def-0.1.2.dist-info/WHEEL
flake8_indent_in_def-0.1.2.dist-info/entry_points.txt
flake8_indent_in_def-0.1.2.dist-info/top_level.txt
flake8_indent_in_def-0.1.2.dist-info/RECORD
