Metadata-Version: 2.1
Name: flake8-indent-in-def
Version: 0.1.2
Summary: A flake8 plugin that enforces 8-space indentation in function/class definitions
Home-page: https://github.com/cyyc1/flake8-indent-in-def
License: MIT
Classifier: License :: OSI Approved :: MIT License
Classifier: Programming Language :: Python :: 3
Classifier: Programming Language :: Python :: 3 :: Only
Classifier: Programming Language :: Python :: Implementation :: CPython
Requires-Python: >=3.8
License-File: LICENSE
Requires-Dist: flake8 (>=4)
